{
  "kind": "singleType",
  "collectionName": "abouts",
  "info": {
    "singularName": "about",
    "pluralName": "abouts",
    "displayName": "About",
    "description": "Write about yourself and the content you create"
  },
  "options": {
    "draftAndPublish": false
  },
  "pluginOptions": {},
  "attributes": {
    "title": {
      "type": "string"
    },
    "our_mission": {
      "type": "richtext"
    },
    "what_we_do": {
      "type": "richtext"
    },
    "where_we_work": {
      "type": "richtext"
    },
    "join_us": {
      "type": "richtext"
    },
    "tagline": {
      "type": "string"
    },
    "tagline_description": {
      "type": "text"
    },
    "banner": {
      "type": "media",
      "multiple": false,
      "required": false,
      "allowedTypes": [
        "images"
      ]
    },
    "banner_description": {
      "type": "text"
    },
    "mission_image": {
      "allowedTypes": [
        "images",
        "files"
      ],
      "type": "media",
      "multiple": false
    }
  }
}
